LICENSE.txt
MANIFEST.in
README.txt
contributors.txt
setup.py
accessible_output/__init__.py
accessible_output/main_output.py
accessible_output/output.py
accessible_output/paths.py
accessible_output/priority.py
accessible_output.egg-info/PKG-INFO
accessible_output.egg-info/SOURCES.txt
accessible_output.egg-info/dependency_links.txt
accessible_output.egg-info/requires.txt
accessible_output.egg-info/top_level.txt
accessible_output/braille/__init__.py
accessible_output/braille/brailler.py
accessible_output/braille/outputs/__init__.py
accessible_output/braille/outputs/jaws.py
accessible_output/braille/outputs/main.py
accessible_output/braille/outputs/nvda.py
accessible_output/braille/outputs/sa.py
accessible_output/braille/outputs/we.py
accessible_output/speech/__init__.py
accessible_output/speech/speaker.py
accessible_output/speech/outputs/__init__.py
accessible_output/speech/outputs/dolphin.py
accessible_output/speech/outputs/jaws.py
accessible_output/speech/outputs/main.py
accessible_output/speech/outputs/nvda.py
accessible_output/speech/outputs/sa.py
accessible_output/speech/outputs/sapi5.py
accessible_output/speech/outputs/sapi5voice.py
accessible_output/speech/outputs/speech_d.py
accessible_output/speech/outputs/speechd_client.py
accessible_output/speech/outputs/speechd_client_new.py
accessible_output/speech/outputs/voiceover.py
accessible_output/speech/outputs/we.py