Metadata-Version: 1.0
Name: accessible-output
Version: 0.7.5
Summary: Library to provide speech and braille output to a variety of different screen readers and other accessibility solutions.
Home-page: http://www.qwitter-client.net
Author: Christopher Toth
Author-email: q@qwitter-client.net
License: UNKNOWN
Platform: UNKNOWN
Classifier: Development Status :: 4 - Beta
Classifier: Intended Audience :: Developers
Classifier: Operating System :: Microsoft :: Windows
Classifier: Programming Language :: Python
Classifier: License :: OSI Approved :: MIT License
Classifier: Topic :: Adaptive Technologies
Classifier: Topic :: Software Development :: Libraries
